{
  "id": "herbhub_soil_percent",
  "title": "Soil Moisture Percent",
  "query": "herbhub_soil_percent",
  "chart_type": "line",
  "unit": "%",
  "generated_at": "2026-05-17T23:00:00Z",
  "start": "2026-05-17T00:00:00Z",
  "end": "2026-05-17T23:59:59Z",
  "step": "5m0s",
  "prometheus_response": {
    "status": "success",
    "data": {
      "resultType": "matrix",
      "result": [
        {
          "metric": {
            "__name__": "herbhub_soil_percent",
            "instance": "172.16.108.193:9100",
            "job": "node-hh",
            "plant": "basil"
          },
          "values": [
            [
              1778976000,
              "46.27"
            ],
            [
              1778976300,
              "46.3"
            ],
            [
              1778976600,
              "46.32"
            ],
            [
              1778976900,
              "46.21"
            ],
            [
              1778977200,
              "46.25"
            ],
            [
              1778977500,
              "46.2"
            ],
            [
              1778977800,
              "46.2"
            ],
            [
              1778978100,
              "46.29"
            ],
            [
              1778978400,
              "47.21"
            ],
            [
              1778978700,
              "46.94"
            ],
            [
              1778979000,
              "53"
            ],
            [
              1778979300,
              "46.17"
            ],
            [
              1778979600,
              "44.43"
            ],
            [
              1778979900,
              "44.44"
            ],
            [
              1778980200,
              "44.46"
            ],
            [
              1778980500,
              "44.43"
            ],
            [
              1778980800,
              "44.48"
            ],
            [
              1778981100,
              "44.51"
            ],
            [
              1778981400,
              "44.51"
            ],
            [
              1778981700,
              "44.53"
            ],
            [
              1778982000,
              "44.51"
            ],
            [
              1778982300,
              "44.55"
            ],
            [
              1778982600,
              "44.63"
            ],
            [
              1778982900,
              "44.61"
            ],
            [
              1778983200,
              "44.67"
            ],
            [
              1778983500,
              "44.67"
            ],
            [
              1778983800,
              "44.72"
            ],
            [
              1778984100,
              "44.77"
            ],
            [
              1778984400,
              "45.01"
            ],
            [
              1778984700,
              "44.95"
            ],
            [
              1778985000,
              "44.96"
            ],
            [
              1778985600,
              "45.04"
            ],
            [
              1778985900,
              "45.07"
            ],
            [
              1778986200,
              "45.11"
            ],
            [
              1778986500,
              "45.03"
            ],
            [
              1778986800,
              "45.02"
            ],
            [
              1778987100,
              "44.97"
            ],
            [
              1778987400,
              "45"
            ],
            [
              1778987700,
              "45.01"
            ],
            [
              1778988000,
              "45.01"
            ],
            [
              1778988300,
              "44.99"
            ],
            [
              1778988600,
              "44.99"
            ],
            [
              1778988900,
              "44.95"
            ],
            [
              1778989200,
              "44.99"
            ],
            [
              1778989500,
              "44.98"
            ],
            [
              1778989800,
              "45.03"
            ],
            [
              1778990100,
              "45.01"
            ],
            [
              1778990400,
              "44.99"
            ],
            [
              1778990700,
              "45.05"
            ],
            [
              1778991000,
              "45.17"
            ],
            [
              1778991300,
              "45.25"
            ],
            [
              1778991600,
              "45.26"
            ],
            [
              1778991900,
              "45.24"
            ],
            [
              1778992200,
              "45.23"
            ],
            [
              1778992500,
              "45.17"
            ],
            [
              1778992800,
              "45.15"
            ],
            [
              1778993100,
              "45.17"
            ],
            [
              1778993400,
              "45.12"
            ],
            [
              1778993700,
              "45.08"
            ],
            [
              1778994000,
              "45.09"
            ],
            [
              1778994300,
              "45.13"
            ],
            [
              1778994600,
              "45.12"
            ],
            [
              1778994900,
              "45.13"
            ],
            [
              1778995200,
              "45.07"
            ],
            [
              1778995500,
              "45.11"
            ],
            [
              1778995800,
              "45.15"
            ],
            [
              1778996100,
              "45.05"
            ],
            [
              1778996400,
              "45.07"
            ],
            [
              1778996700,
              "45.04"
            ],
            [
              1778997000,
              "45.03"
            ],
            [
              1778997300,
              "45.04"
            ],
            [
              1778997600,
              "45.01"
            ],
            [
              1778997900,
              "44.98"
            ],
            [
              1778998200,
              "44.96"
            ],
            [
              1778998500,
              "45.28"
            ],
            [
              1778998800,
              "45.11"
            ],
            [
              1778999100,
              "45.08"
            ],
            [
              1778999400,
              "44.84"
            ],
            [
              1778999700,
              "44.82"
            ],
            [
              1779000000,
              "44.77"
            ],
            [
              1779000300,
              "44.82"
            ],
            [
              1779000600,
              "44.84"
            ],
            [
              1779000900,
              "44.75"
            ],
            [
              1779001200,
              "44.71"
            ],
            [
              1779001500,
              "44.77"
            ],
            [
              1779001800,
              "44.73"
            ],
            [
              1779002100,
              "44.67"
            ],
            [
              1779002400,
              "44.55"
            ],
            [
              1779002700,
              "44.38"
            ],
            [
              1779003000,
              "44.36"
            ],
            [
              1779003300,
              "44.47"
            ],
            [
              1779003600,
              "44.42"
            ],
            [
              1779003900,
              "44.28"
            ],
            [
              1779004200,
              "44.03"
            ],
            [
              1779004500,
              "43.94"
            ],
            [
              1779004800,
              "43.86"
            ],
            [
              1779005100,
              "43.83"
            ],
            [
              1779005400,
              "43.75"
            ],
            [
              1779005700,
              "43.74"
            ],
            [
              1779006000,
              "43.74"
            ],
            [
              1779006300,
              "43.69"
            ],
            [
              1779006600,
              "43.59"
            ],
            [
              1779006900,
              "44.01"
            ],
            [
              1779007200,
              "83.79"
            ],
            [
              1779007500,
              "84.22"
            ],
            [
              1779007800,
              "84.3"
            ],
            [
              1779008100,
              "84.53"
            ],
            [
              1779008400,
              "84.66"
            ],
            [
              1779008700,
              "85.52"
            ],
            [
              1779009000,
              "85.84"
            ],
            [
              1779009300,
              "85.85"
            ],
            [
              1779009600,
              "85.6"
            ],
            [
              1779009900,
              "84.48"
            ],
            [
              1779010200,
              "83.35"
            ],
            [
              1779010500,
              "82.06"
            ],
            [
              1779010800,
              "81.36"
            ],
            [
              1779011100,
              "80.78"
            ],
            [
              1779011400,
              "80.24"
            ],
            [
              1779011700,
              "79.71"
            ],
            [
              1779012000,
              "79.26"
            ],
            [
              1779012300,
              "78.7"
            ],
            [
              1779012600,
              "78.27"
            ],
            [
              1779012900,
              "77.96"
            ],
            [
              1779013200,
              "77.58"
            ],
            [
              1779013500,
              "77.42"
            ],
            [
              1779013800,
              "77.07"
            ],
            [
              1779014100,
              "76.84"
            ],
            [
              1779014400,
              "76.62"
            ],
            [
              1779014700,
              "76.33"
            ],
            [
              1779015000,
              "75.99"
            ],
            [
              1779015300,
              "75.75"
            ],
            [
              1779015600,
              "75.51"
            ],
            [
              1779015900,
              "75.28"
            ],
            [
              1779016200,
              "75.04"
            ],
            [
              1779016500,
              "74.96"
            ],
            [
              1779016800,
              "74.58"
            ],
            [
              1779017100,
              "74.41"
            ],
            [
              1779017400,
              "74.33"
            ],
            [
              1779017700,
              "74.21"
            ],
            [
              1779018000,
              "73.96"
            ],
            [
              1779018300,
              "73.72"
            ],
            [
              1779018600,
              "74.12"
            ],
            [
              1779018900,
              "74.08"
            ],
            [
              1779019200,
              "73.89"
            ],
            [
              1779019500,
              "73.81"
            ],
            [
              1779019800,
              "73.49"
            ],
            [
              1779020100,
              "73.37"
            ],
            [
              1779020400,
              "73.21"
            ],
            [
              1779020700,
              "73.41"
            ],
            [
              1779021000,
              "73.54"
            ],
            [
              1779021300,
              "73.39"
            ],
            [
              1779021600,
              "73.13"
            ],
            [
              1779021900,
              "72.64"
            ],
            [
              1779022200,
              "73.35"
            ],
            [
              1779022500,
              "74.63"
            ],
            [
              1779022800,
              "73.97"
            ],
            [
              1779023100,
              "75.09"
            ],
            [
              1779023400,
              "74.46"
            ],
            [
              1779023700,
              "74.93"
            ],
            [
              1779024000,
              "75.14"
            ],
            [
              1779024300,
              "75.49"
            ],
            [
              1779024600,
              "75.27"
            ],
            [
              1779024900,
              "75"
            ],
            [
              1779025200,
              "74.17"
            ],
            [
              1779025500,
              "74.41"
            ],
            [
              1779025800,
              "74.35"
            ],
            [
              1779026100,
              "73.75"
            ],
            [
              1779026400,
              "74.31"
            ],
            [
              1779026700,
              "73.8"
            ],
            [
              1779027000,
              "73.39"
            ],
            [
              1779027300,
              "73.22"
            ],
            [
              1779027600,
              "72.44"
            ],
            [
              1779027900,
              "72.05"
            ],
            [
              1779028200,
              "71.94"
            ],
            [
              1779028500,
              "72.94"
            ],
            [
              1779028800,
              "72.93"
            ],
            [
              1779029100,
              "72.91"
            ],
            [
              1779029400,
              "72.83"
            ],
            [
              1779029700,
              "72.5"
            ],
            [
              1779030000,
              "72.06"
            ],
            [
              1779030300,
              "73.06"
            ],
            [
              1779030600,
              "78.83"
            ],
            [
              1779030900,
              "72.85"
            ],
            [
              1779031200,
              "71.93"
            ],
            [
              1779031500,
              "77.42"
            ],
            [
              1779031800,
              "76.74"
            ],
            [
              1779032100,
              "75.38"
            ],
            [
              1779032400,
              "72.06"
            ],
            [
              1779032700,
              "71.5"
            ],
            [
              1779033000,
              "70.93"
            ],
            [
              1779033300,
              "70.76"
            ],
            [
              1779033600,
              "70.68"
            ],
            [
              1779033900,
              "74.5"
            ],
            [
              1779034200,
              "74.1"
            ],
            [
              1779034500,
              "73.93"
            ],
            [
              1779034800,
              "73.84"
            ],
            [
              1779035100,
              "73.5"
            ],
            [
              1779035400,
              "73.46"
            ],
            [
              1779035700,
              "73.31"
            ],
            [
              1779036000,
              "73.66"
            ],
            [
              1779036300,
              "73.1"
            ],
            [
              1779036600,
              "73.89"
            ],
            [
              1779036900,
              "73.85"
            ],
            [
              1779037200,
              "73.75"
            ],
            [
              1779037500,
              "73.72"
            ],
            [
              1779037800,
              "73.7"
            ],
            [
              1779038100,
              "74.46"
            ],
            [
              1779038400,
              "74.3"
            ],
            [
              1779038700,
              "73.74"
            ],
            [
              1779039000,
              "70.97"
            ],
            [
              1779039300,
              "73.16"
            ],
            [
              1779039600,
              "73.13"
            ],
            [
              1779039900,
              "73.16"
            ],
            [
              1779040200,
              "72.18"
            ],
            [
              1779040500,
              "72.66"
            ],
            [
              1779040800,
              "72.47"
            ],
            [
              1779041100,
              "72.5"
            ],
            [
              1779041400,
              "72.41"
            ],
            [
              1779041700,
              "72.31"
            ],
            [
              1779042000,
              "70.75"
            ],
            [
              1779042300,
              "70.31"
            ],
            [
              1779042600,
              "70.64"
            ],
            [
              1779042900,
              "70.46"
            ],
            [
              1779043200,
              "70.39"
            ],
            [
              1779043500,
              "70.57"
            ],
            [
              1779043800,
              "71.72"
            ],
            [
              1779044100,
              "70.15"
            ],
            [
              1779044400,
              "70.64"
            ],
            [
              1779044700,
              "70.61"
            ],
            [
              1779045000,
              "70.65"
            ],
            [
              1779045300,
              "70.59"
            ],
            [
              1779045600,
              "70.52"
            ],
            [
              1779045900,
              "70.38"
            ],
            [
              1779046200,
              "70.28"
            ],
            [
              1779046500,
              "70.34"
            ],
            [
              1779046800,
              "70.28"
            ],
            [
              1779047100,
              "70.24"
            ],
            [
              1779047400,
              "70.02"
            ],
            [
              1779047700,
              "70.04"
            ],
            [
              1779048000,
              "70.1"
            ],
            [
              1779048300,
              "69.92"
            ],
            [
              1779048600,
              "69.93"
            ],
            [
              1779048900,
              "70.01"
            ],
            [
              1779049200,
              "69.65"
            ],
            [
              1779049500,
              "69.45"
            ],
            [
              1779049800,
              "69.35"
            ],
            [
              1779050100,
              "69.24"
            ],
            [
              1779050400,
              "69.34"
            ],
            [
              1779050700,
              "69.43"
            ],
            [
              1779051000,
              "69.46"
            ],
            [
              1779051300,
              "69.4"
            ],
            [
              1779051600,
              "69.42"
            ],
            [
              1779051900,
              "69.48"
            ],
            [
              1779052200,
              "69.5"
            ],
            [
              1779052500,
              "69.45"
            ],
            [
              1779052800,
              "69.39"
            ],
            [
              1779053100,
              "69.4"
            ],
            [
              1779053400,
              "69.35"
            ],
            [
              1779053700,
              "69.53"
            ],
            [
              1779054000,
              "69.69"
            ],
            [
              1779054300,
              "69.67"
            ],
            [
              1779054600,
              "69.6"
            ],
            [
              1779054900,
              "69.6"
            ],
            [
              1779055200,
              "69.52"
            ],
            [
              1779055500,
              "69.4"
            ],
            [
              1779055800,
              "69.4"
            ],
            [
              1779056100,
              "69.27"
            ],
            [
              1779056400,
              "69.14"
            ],
            [
              1779056700,
              "69.09"
            ],
            [
              1779057000,
              "69.01"
            ],
            [
              1779057300,
              "69.01"
            ],
            [
              1779057600,
              "68.97"
            ],
            [
              1779057900,
              "68.99"
            ],
            [
              1779058200,
              "68.95"
            ],
            [
              1779058500,
              "68.96"
            ],
            [
              1779058800,
              "68.93"
            ]
          ]
        },
        {
          "metric": {
            "__name__": "herbhub_soil_percent",
            "instance": "172.16.108.193:9100",
            "job": "node-hh",
            "plant": "chilli"
          },
          "values": [
            [
              1778976000,
              "43.41"
            ],
            [
              1778976300,
              "43.39"
            ],
            [
              1778976600,
              "43.4"
            ],
            [
              1778976900,
              "43.39"
            ],
            [
              1778977200,
              "43.42"
            ],
            [
              1778977500,
              "43.38"
            ],
            [
              1778977800,
              "43.37"
            ],
            [
              1778978100,
              "43.29"
            ],
            [
              1778978400,
              "42.68"
            ],
            [
              1778978700,
              "42.85"
            ],
            [
              1778979000,
              "41.23"
            ],
            [
              1778979300,
              "43.29"
            ],
            [
              1778979600,
              "45.11"
            ],
            [
              1778979900,
              "45.07"
            ],
            [
              1778980200,
              "44.98"
            ],
            [
              1778980500,
              "44.95"
            ],
            [
              1778980800,
              "44.91"
            ],
            [
              1778981100,
              "44.91"
            ],
            [
              1778981400,
              "44.88"
            ],
            [
              1778981700,
              "44.84"
            ],
            [
              1778982000,
              "44.83"
            ],
            [
              1778982300,
              "44.83"
            ],
            [
              1778982600,
              "44.8"
            ],
            [
              1778982900,
              "44.78"
            ],
            [
              1778983200,
              "44.76"
            ],
            [
              1778983500,
              "44.74"
            ],
            [
              1778983800,
              "44.72"
            ],
            [
              1778984100,
              "44.59"
            ],
            [
              1778984400,
              "44.44"
            ],
            [
              1778984700,
              "44.41"
            ],
            [
              1778985000,
              "44.42"
            ],
            [
              1778985600,
              "44.36"
            ],
            [
              1778985900,
              "44.34"
            ],
            [
              1778986200,
              "44.34"
            ],
            [
              1778986500,
              "44.34"
            ],
            [
              1778986800,
              "44.36"
            ],
            [
              1778987100,
              "44.33"
            ],
            [
              1778987400,
              "44.32"
            ],
            [
              1778987700,
              "44.28"
            ],
            [
              1778988000,
              "44.33"
            ],
            [
              1778988300,
              "44.36"
            ],
            [
              1778988600,
              "44.36"
            ],
            [
              1778988900,
              "44.33"
            ],
            [
              1778989200,
              "44.32"
            ],
            [
              1778989500,
              "44.33"
            ],
            [
              1778989800,
              "44.33"
            ],
            [
              1778990100,
              "44.32"
            ],
            [
              1778990400,
              "44.32"
            ],
            [
              1778990700,
              "44.29"
            ],
            [
              1778991000,
              "44.29"
            ],
            [
              1778991300,
              "44.29"
            ],
            [
              1778991600,
              "44.25"
            ],
            [
              1778991900,
              "44.22"
            ],
            [
              1778992200,
              "44.19"
            ],
            [
              1778992500,
              "44.19"
            ],
            [
              1778992800,
              "44.17"
            ],
            [
              1778993100,
              "44.17"
            ],
            [
              1778993400,
              "44.17"
            ],
            [
              1778993700,
              "44.13"
            ],
            [
              1778994000,
              "44.11"
            ],
            [
              1778994300,
              "44.1"
            ],
            [
              1778994600,
              "44.07"
            ],
            [
              1778994900,
              "44.06"
            ],
            [
              1778995200,
              "44.03"
            ],
            [
              1778995500,
              "44.04"
            ],
            [
              1778995800,
              "44.01"
            ],
            [
              1778996100,
              "43.99"
            ],
            [
              1778996400,
              "43.98"
            ],
            [
              1778996700,
              "44"
            ],
            [
              1778997000,
              "43.94"
            ],
            [
              1778997300,
              "43.92"
            ],
            [
              1778997600,
              "43.9"
            ],
            [
              1778997900,
              "43.87"
            ],
            [
              1778998200,
              "43.81"
            ],
            [
              1778998500,
              "43.45"
            ],
            [
              1778998800,
              "43.6"
            ],
            [
              1778999100,
              "43.61"
            ],
            [
              1778999400,
              "43.82"
            ],
            [
              1778999700,
              "43.82"
            ],
            [
              1779000000,
              "43.82"
            ],
            [
              1779000300,
              "43.83"
            ],
            [
              1779000600,
              "43.83"
            ],
            [
              1779000900,
              "43.85"
            ],
            [
              1779001200,
              "43.81"
            ],
            [
              1779001500,
              "43.78"
            ],
            [
              1779001800,
              "43.73"
            ],
            [
              1779002100,
              "43.71"
            ],
            [
              1779002400,
              "43.68"
            ],
            [
              1779002700,
              "43.64"
            ],
            [
              1779003000,
              "43.63"
            ],
            [
              1779003300,
              "43.52"
            ],
            [
              1779003600,
              "43.55"
            ],
            [
              1779003900,
              "43.49"
            ],
            [
              1779004200,
              "43.55"
            ],
            [
              1779004500,
              "43.52"
            ],
            [
              1779004800,
              "43.49"
            ],
            [
              1779005100,
              "43.52"
            ],
            [
              1779005400,
              "43.55"
            ],
            [
              1779005700,
              "43.58"
            ],
            [
              1779006000,
              "43.58"
            ],
            [
              1779006300,
              "43.58"
            ],
            [
              1779006600,
              "43.58"
            ],
            [
              1779006900,
              "68.34"
            ],
            [
              1779007200,
              "65.65"
            ],
            [
              1779007500,
              "66.18"
            ],
            [
              1779007800,
              "66.1"
            ],
            [
              1779008100,
              "66.11"
            ],
            [
              1779008400,
              "66.19"
            ],
            [
              1779008700,
              "65.98"
            ],
            [
              1779009000,
              "65.35"
            ],
            [
              1779009300,
              "65.03"
            ],
            [
              1779009600,
              "64.65"
            ],
            [
              1779009900,
              "64.5"
            ],
            [
              1779010200,
              "64.47"
            ],
            [
              1779010500,
              "64.45"
            ],
            [
              1779010800,
              "64.42"
            ],
            [
              1779011100,
              "64.2"
            ],
            [
              1779011400,
              "64.2"
            ],
            [
              1779011700,
              "64.15"
            ],
            [
              1779012000,
              "64.09"
            ],
            [
              1779012300,
              "63.94"
            ],
            [
              1779012600,
              "63.88"
            ],
            [
              1779012900,
              "63.8"
            ],
            [
              1779013200,
              "63.72"
            ],
            [
              1779013500,
              "63.69"
            ],
            [
              1779013800,
              "63.62"
            ],
            [
              1779014100,
              "63.55"
            ],
            [
              1779014400,
              "63.48"
            ],
            [
              1779014700,
              "63.38"
            ],
            [
              1779015000,
              "63.27"
            ],
            [
              1779015300,
              "63.24"
            ],
            [
              1779015600,
              "63.16"
            ],
            [
              1779015900,
              "63.1"
            ],
            [
              1779016200,
              "62.97"
            ],
            [
              1779016500,
              "62.89"
            ],
            [
              1779016800,
              "62.81"
            ],
            [
              1779017100,
              "62.79"
            ],
            [
              1779017400,
              "62.81"
            ],
            [
              1779017700,
              "62.75"
            ],
            [
              1779018000,
              "62.64"
            ],
            [
              1779018300,
              "62.55"
            ],
            [
              1779018600,
              "62.79"
            ],
            [
              1779018900,
              "62.81"
            ],
            [
              1779019200,
              "62.74"
            ],
            [
              1779019500,
              "62.73"
            ],
            [
              1779019800,
              "62.54"
            ],
            [
              1779020100,
              "62.4"
            ],
            [
              1779020400,
              "62.26"
            ],
            [
              1779020700,
              "62.26"
            ],
            [
              1779021000,
              "62.1"
            ],
            [
              1779021300,
              "61.98"
            ],
            [
              1779021600,
              "61.93"
            ],
            [
              1779021900,
              "61.71"
            ],
            [
              1779022200,
              "62.08"
            ],
            [
              1779022500,
              "62.65"
            ],
            [
              1779022800,
              "61.89"
            ],
            [
              1779023100,
              "62.2"
            ],
            [
              1779023400,
              "61.74"
            ],
            [
              1779023700,
              "61.05"
            ],
            [
              1779024000,
              "61.2"
            ],
            [
              1779024300,
              "61.21"
            ],
            [
              1779024600,
              "61.16"
            ],
            [
              1779024900,
              "61.17"
            ],
            [
              1779025200,
              "61.07"
            ],
            [
              1779025500,
              "60.48"
            ],
            [
              1779025800,
              "60.79"
            ],
            [
              1779026100,
              "60.78"
            ],
            [
              1779026400,
              "60.22"
            ],
            [
              1779026700,
              "60.13"
            ],
            [
              1779027000,
              "60.11"
            ],
            [
              1779027300,
              "60.06"
            ],
            [
              1779027600,
              "60.64"
            ],
            [
              1779027900,
              "60.34"
            ],
            [
              1779028200,
              "60.17"
            ],
            [
              1779028500,
              "60.49"
            ],
            [
              1779028800,
              "60.14"
            ],
            [
              1779029100,
              "60.48"
            ],
            [
              1779029400,
              "60.61"
            ],
            [
              1779029700,
              "60.27"
            ],
            [
              1779030000,
              "60.25"
            ],
            [
              1779030300,
              "59.83"
            ],
            [
              1779030600,
              "56.21"
            ],
            [
              1779030900,
              "60.4"
            ],
            [
              1779031200,
              "61.2"
            ],
            [
              1779031500,
              "57.08"
            ],
            [
              1779031800,
              "57.2"
            ],
            [
              1779032100,
              "57.9"
            ],
            [
              1779032400,
              "61.55"
            ],
            [
              1779032700,
              "61.4"
            ],
            [
              1779033000,
              "61.24"
            ],
            [
              1779033300,
              "60.8"
            ],
            [
              1779033600,
              "60.67"
            ],
            [
              1779033900,
              "56.89"
            ],
            [
              1779034200,
              "56.72"
            ],
            [
              1779034500,
              "56.79"
            ],
            [
              1779034800,
              "56.83"
            ],
            [
              1779035100,
              "56.91"
            ],
            [
              1779035400,
              "56.9"
            ],
            [
              1779035700,
              "57.01"
            ],
            [
              1779036000,
              "56.98"
            ],
            [
              1779036300,
              "57.37"
            ],
            [
              1779036600,
              "56.79"
            ],
            [
              1779036900,
              "56.76"
            ],
            [
              1779037200,
              "56.75"
            ],
            [
              1779037500,
              "56.73"
            ],
            [
              1779037800,
              "56.73"
            ],
            [
              1779038100,
              "57.06"
            ],
            [
              1779038400,
              "57.02"
            ],
            [
              1779038700,
              "57.28"
            ],
            [
              1779039000,
              "59.92"
            ],
            [
              1779039300,
              "57.86"
            ],
            [
              1779039600,
              "57.73"
            ],
            [
              1779039900,
              "57.55"
            ],
            [
              1779040200,
              "58.61"
            ],
            [
              1779040500,
              "57.54"
            ],
            [
              1779040800,
              "57.6"
            ],
            [
              1779041100,
              "57.52"
            ],
            [
              1779041400,
              "57.55"
            ],
            [
              1779041700,
              "57.54"
            ],
            [
              1779042000,
              "59.09"
            ],
            [
              1779042300,
              "59.49"
            ],
            [
              1779042600,
              "59.12"
            ],
            [
              1779042900,
              "59.16"
            ],
            [
              1779043200,
              "59.06"
            ],
            [
              1779043500,
              "58.74"
            ],
            [
              1779043800,
              "57.55"
            ],
            [
              1779044100,
              "59.12"
            ],
            [
              1779044400,
              "58.57"
            ],
            [
              1779044700,
              "58.53"
            ],
            [
              1779045000,
              "58.47"
            ],
            [
              1779045300,
              "58.47"
            ],
            [
              1779045600,
              "58.47"
            ],
            [
              1779045900,
              "58.6"
            ],
            [
              1779046200,
              "58.53"
            ],
            [
              1779046500,
              "58.5"
            ],
            [
              1779046800,
              "58.44"
            ],
            [
              1779047100,
              "58.44"
            ],
            [
              1779047400,
              "58.62"
            ],
            [
              1779047700,
              "58.55"
            ],
            [
              1779048000,
              "58.4"
            ],
            [
              1779048300,
              "58.57"
            ],
            [
              1779048600,
              "58.49"
            ],
            [
              1779048900,
              "58.51"
            ],
            [
              1779049200,
              "58.5"
            ],
            [
              1779049500,
              "58.57"
            ],
            [
              1779049800,
              "58.59"
            ],
            [
              1779050100,
              "58.54"
            ],
            [
              1779050400,
              "58.44"
            ],
            [
              1779050700,
              "58.4"
            ],
            [
              1779051000,
              "58.38"
            ],
            [
              1779051300,
              "58.38"
            ],
            [
              1779051600,
              "58.31"
            ],
            [
              1779051900,
              "58.31"
            ],
            [
              1779052200,
              "58.31"
            ],
            [
              1779052500,
              "58.31"
            ],
            [
              1779052800,
              "58.31"
            ],
            [
              1779053100,
              "58.32"
            ],
            [
              1779053400,
              "58.3"
            ],
            [
              1779053700,
              "58.32"
            ],
            [
              1779054000,
              "58.5"
            ],
            [
              1779054300,
              "58.54"
            ],
            [
              1779054600,
              "58.54"
            ],
            [
              1779054900,
              "58.51"
            ],
            [
              1779055200,
              "58.47"
            ],
            [
              1779055500,
              "58.45"
            ],
            [
              1779055800,
              "58.41"
            ],
            [
              1779056100,
              "58.44"
            ],
            [
              1779056400,
              "58.59"
            ],
            [
              1779056700,
              "58.58"
            ],
            [
              1779057000,
              "58.51"
            ],
            [
              1779057300,
              "58.43"
            ],
            [
              1779057600,
              "58.43"
            ],
            [
              1779057900,
              "58.4"
            ],
            [
              1779058200,
              "58.31"
            ],
            [
              1779058500,
              "58.17"
            ],
            [
              1779058800,
              "58.09"
            ]
          ]
        },
        {
          "metric": {
            "__name__": "herbhub_soil_percent",
            "instance": "172.16.108.193:9100",
            "job": "node-hh",
            "plant": "oregano"
          },
          "values": [
            [
              1778976000,
              "38.05"
            ],
            [
              1778976300,
              "38.06"
            ],
            [
              1778976600,
              "38.06"
            ],
            [
              1778976900,
              "38.06"
            ],
            [
              1778977200,
              "38.1"
            ],
            [
              1778977500,
              "38.05"
            ],
            [
              1778977800,
              "38.04"
            ],
            [
              1778978100,
              "37.94"
            ],
            [
              1778978400,
              "37.04"
            ],
            [
              1778978700,
              "37.27"
            ],
            [
              1778979000,
              "33.66"
            ],
            [
              1778979300,
              "38.01"
            ],
            [
              1778979600,
              "40.13"
            ],
            [
              1778979900,
              "40.16"
            ],
            [
              1778980200,
              "40.03"
            ],
            [
              1778980500,
              "39.98"
            ],
            [
              1778980800,
              "39.93"
            ],
            [
              1778981100,
              "39.9"
            ],
            [
              1778981400,
              "39.86"
            ],
            [
              1778981700,
              "39.81"
            ],
            [
              1778982000,
              "39.8"
            ],
            [
              1778982300,
              "39.78"
            ],
            [
              1778982600,
              "39.78"
            ],
            [
              1778982900,
              "39.74"
            ],
            [
              1778983200,
              "39.74"
            ],
            [
              1778983500,
              "39.72"
            ],
            [
              1778983800,
              "39.69"
            ],
            [
              1778984100,
              "39.55"
            ],
            [
              1778984400,
              "39.39"
            ],
            [
              1778984700,
              "39.38"
            ],
            [
              1778985000,
              "39.39"
            ],
            [
              1778985600,
              "39.31"
            ],
            [
              1778985900,
              "39.33"
            ],
            [
              1778986200,
              "39.31"
            ],
            [
              1778986500,
              "39.33"
            ],
            [
              1778986800,
              "39.35"
            ],
            [
              1778987100,
              "39.31"
            ],
            [
              1778987400,
              "39.29"
            ],
            [
              1778987700,
              "39.27"
            ],
            [
              1778988000,
              "39.34"
            ],
            [
              1778988300,
              "39.38"
            ],
            [
              1778988600,
              "39.38"
            ],
            [
              1778988900,
              "39.37"
            ],
            [
              1778989200,
              "39.31"
            ],
            [
              1778989500,
              "39.33"
            ],
            [
              1778989800,
              "39.37"
            ],
            [
              1778990100,
              "39.37"
            ],
            [
              1778990400,
              "39.35"
            ],
            [
              1778990700,
              "39.3"
            ],
            [
              1778991000,
              "39.34"
            ],
            [
              1778991300,
              "39.34"
            ],
            [
              1778991600,
              "39.29"
            ],
            [
              1778991900,
              "39.25"
            ],
            [
              1778992200,
              "39.26"
            ],
            [
              1778992500,
              "39.27"
            ],
            [
              1778992800,
              "39.25"
            ],
            [
              1778993100,
              "39.25"
            ],
            [
              1778993400,
              "39.25"
            ],
            [
              1778993700,
              "39.18"
            ],
            [
              1778994000,
              "39.16"
            ],
            [
              1778994300,
              "39.16"
            ],
            [
              1778994600,
              "39.17"
            ],
            [
              1778994900,
              "39.17"
            ],
            [
              1778995200,
              "39.13"
            ],
            [
              1778995500,
              "39.13"
            ],
            [
              1778995800,
              "39.12"
            ],
            [
              1778996100,
              "39.08"
            ],
            [
              1778996400,
              "39.11"
            ],
            [
              1778996700,
              "39.09"
            ],
            [
              1778997000,
              "39.07"
            ],
            [
              1778997300,
              "39.03"
            ],
            [
              1778997600,
              "39.03"
            ],
            [
              1778997900,
              "38.95"
            ],
            [
              1778998200,
              "38.9"
            ],
            [
              1778998500,
              "38.51"
            ],
            [
              1778998800,
              "38.69"
            ],
            [
              1778999100,
              "38.73"
            ],
            [
              1778999400,
              "38.87"
            ],
            [
              1778999700,
              "38.86"
            ],
            [
              1779000000,
              "38.9"
            ],
            [
              1779000300,
              "38.91"
            ],
            [
              1779000600,
              "38.95"
            ],
            [
              1779000900,
              "38.92"
            ],
            [
              1779001200,
              "38.83"
            ],
            [
              1779001500,
              "38.79"
            ],
            [
              1779001800,
              "38.72"
            ],
            [
              1779002100,
              "38.65"
            ],
            [
              1779002400,
              "38.6"
            ],
            [
              1779002700,
              "38.47"
            ],
            [
              1779003000,
              "38.46"
            ],
            [
              1779003300,
              "38.34"
            ],
            [
              1779003600,
              "38.38"
            ],
            [
              1779003900,
              "38.23"
            ],
            [
              1779004200,
              "38.29"
            ],
            [
              1779004500,
              "38.2"
            ],
            [
              1779004800,
              "38.16"
            ],
            [
              1779005100,
              "38.14"
            ],
            [
              1779005400,
              "38.18"
            ],
            [
              1779005700,
              "38.17"
            ],
            [
              1779006000,
              "38.16"
            ],
            [
              1779006300,
              "38.17"
            ],
            [
              1779006600,
              "38.16"
            ],
            [
              1779006900,
              "37.78"
            ],
            [
              1779007200,
              "85.31"
            ],
            [
              1779007500,
              "83.71"
            ],
            [
              1779007800,
              "82.97"
            ],
            [
              1779008100,
              "82.77"
            ],
            [
              1779008400,
              "82.73"
            ],
            [
              1779008700,
              "82.55"
            ],
            [
              1779009000,
              "81.92"
            ],
            [
              1779009300,
              "81.21"
            ],
            [
              1779009600,
              "80.33"
            ],
            [
              1779009900,
              "79.31"
            ],
            [
              1779010200,
              "78.27"
            ],
            [
              1779010500,
              "77.45"
            ],
            [
              1779010800,
              "76.68"
            ],
            [
              1779011100,
              "75.95"
            ],
            [
              1779011400,
              "75.38"
            ],
            [
              1779011700,
              "74.8"
            ],
            [
              1779012000,
              "74.11"
            ],
            [
              1779012300,
              "73.33"
            ],
            [
              1779012600,
              "72.81"
            ],
            [
              1779012900,
              "72.3"
            ],
            [
              1779013200,
              "71.75"
            ],
            [
              1779013500,
              "71.34"
            ],
            [
              1779013800,
              "70.95"
            ],
            [
              1779014100,
              "70.57"
            ],
            [
              1779014400,
              "70.3"
            ],
            [
              1779014700,
              "69.96"
            ],
            [
              1779015000,
              "69.54"
            ],
            [
              1779015300,
              "69.23"
            ],
            [
              1779015600,
              "68.97"
            ],
            [
              1779015900,
              "68.71"
            ],
            [
              1779016200,
              "68.5"
            ],
            [
              1779016500,
              "68.24"
            ],
            [
              1779016800,
              "67.86"
            ],
            [
              1779017100,
              "67.6"
            ],
            [
              1779017400,
              "67.38"
            ],
            [
              1779017700,
              "67.3"
            ],
            [
              1779018000,
              "67.1"
            ],
            [
              1779018300,
              "66.76"
            ],
            [
              1779018600,
              "66.8"
            ],
            [
              1779018900,
              "66.5"
            ],
            [
              1779019200,
              "66.36"
            ],
            [
              1779019500,
              "66.28"
            ],
            [
              1779019800,
              "65.98"
            ],
            [
              1779020100,
              "65.73"
            ],
            [
              1779020400,
              "65.44"
            ],
            [
              1779020700,
              "65.51"
            ],
            [
              1779021000,
              "65.38"
            ],
            [
              1779021300,
              "65.15"
            ],
            [
              1779021600,
              "64.89"
            ],
            [
              1779021900,
              "64.27"
            ],
            [
              1779022200,
              "64.37"
            ],
            [
              1779022500,
              "64.91"
            ],
            [
              1779022800,
              "64.04"
            ],
            [
              1779023100,
              "64.38"
            ],
            [
              1779023400,
              "63.96"
            ],
            [
              1779023700,
              "63.36"
            ],
            [
              1779024000,
              "63.61"
            ],
            [
              1779024300,
              "63.58"
            ],
            [
              1779024600,
              "63.44"
            ],
            [
              1779024900,
              "63.07"
            ],
            [
              1779025200,
              "62.48"
            ],
            [
              1779025500,
              "61.66"
            ],
            [
              1779025800,
              "61.83"
            ],
            [
              1779026100,
              "61.74"
            ],
            [
              1779026400,
              "61.14"
            ],
            [
              1779026700,
              "61.05"
            ],
            [
              1779027000,
              "61"
            ],
            [
              1779027300,
              "60.83"
            ],
            [
              1779027600,
              "61.09"
            ],
            [
              1779027900,
              "60.65"
            ],
            [
              1779028200,
              "60.44"
            ],
            [
              1779028500,
              "61.02"
            ],
            [
              1779028800,
              "60.57"
            ],
            [
              1779029100,
              "60.59"
            ],
            [
              1779029400,
              "60.49"
            ],
            [
              1779029700,
              "60.02"
            ],
            [
              1779030000,
              "59.99"
            ],
            [
              1779030300,
              "59.63"
            ],
            [
              1779030600,
              "54.82"
            ],
            [
              1779030900,
              "60.32"
            ],
            [
              1779031200,
              "61"
            ],
            [
              1779031500,
              "56.07"
            ],
            [
              1779031800,
              "56.35"
            ],
            [
              1779032100,
              "57.3"
            ],
            [
              1779032400,
              "61.01"
            ],
            [
              1779032700,
              "60.78"
            ],
            [
              1779033000,
              "60.2"
            ],
            [
              1779033300,
              "59.54"
            ],
            [
              1779033600,
              "59.21"
            ],
            [
              1779033900,
              "55.13"
            ],
            [
              1779034200,
              "55.09"
            ],
            [
              1779034500,
              "55.23"
            ],
            [
              1779034800,
              "55.2"
            ],
            [
              1779035100,
              "55.12"
            ],
            [
              1779035400,
              "55.09"
            ],
            [
              1779035700,
              "55.29"
            ],
            [
              1779036000,
              "55.3"
            ],
            [
              1779036300,
              "55.77"
            ],
            [
              1779036600,
              "55.01"
            ],
            [
              1779036900,
              "54.94"
            ],
            [
              1779037200,
              "54.82"
            ],
            [
              1779037500,
              "54.68"
            ],
            [
              1779037800,
              "54.66"
            ],
            [
              1779038100,
              "55.08"
            ],
            [
              1779038400,
              "55.03"
            ],
            [
              1779038700,
              "55.3"
            ],
            [
              1779039000,
              "58.23"
            ],
            [
              1779039300,
              "55.98"
            ],
            [
              1779039600,
              "55.79"
            ],
            [
              1779039900,
              "55.57"
            ],
            [
              1779040200,
              "56.78"
            ],
            [
              1779040500,
              "55.44"
            ],
            [
              1779040800,
              "55.44"
            ],
            [
              1779041100,
              "55.26"
            ],
            [
              1779041400,
              "55.23"
            ],
            [
              1779041700,
              "55.25"
            ],
            [
              1779042000,
              "56.94"
            ],
            [
              1779042300,
              "57.28"
            ],
            [
              1779042600,
              "56.85"
            ],
            [
              1779042900,
              "56.85"
            ],
            [
              1779043200,
              "56.68"
            ],
            [
              1779043500,
              "56.26"
            ],
            [
              1779043800,
              "54.87"
            ],
            [
              1779044100,
              "56.6"
            ],
            [
              1779044400,
              "56"
            ],
            [
              1779044700,
              "55.96"
            ],
            [
              1779045000,
              "55.87"
            ],
            [
              1779045300,
              "55.83"
            ],
            [
              1779045600,
              "55.78"
            ],
            [
              1779045900,
              "55.83"
            ],
            [
              1779046200,
              "55.74"
            ],
            [
              1779046500,
              "55.65"
            ],
            [
              1779046800,
              "55.55"
            ],
            [
              1779047100,
              "55.51"
            ],
            [
              1779047400,
              "55.66"
            ],
            [
              1779047700,
              "55.57"
            ],
            [
              1779048000,
              "55.38"
            ],
            [
              1779048300,
              "55.49"
            ],
            [
              1779048600,
              "55.44"
            ],
            [
              1779048900,
              "55.46"
            ],
            [
              1779049200,
              "55.44"
            ],
            [
              1779049500,
              "55.46"
            ],
            [
              1779049800,
              "55.44"
            ],
            [
              1779050100,
              "55.36"
            ],
            [
              1779050400,
              "55.25"
            ],
            [
              1779050700,
              "55.18"
            ],
            [
              1779051000,
              "55.16"
            ],
            [
              1779051300,
              "55.1"
            ],
            [
              1779051600,
              "55.03"
            ],
            [
              1779051900,
              "55"
            ],
            [
              1779052200,
              "54.96"
            ],
            [
              1779052500,
              "54.97"
            ],
            [
              1779052800,
              "54.93"
            ],
            [
              1779053100,
              "54.94"
            ],
            [
              1779053400,
              "54.87"
            ],
            [
              1779053700,
              "54.88"
            ],
            [
              1779054000,
              "55.06"
            ],
            [
              1779054300,
              "55.12"
            ],
            [
              1779054600,
              "55.08"
            ],
            [
              1779054900,
              "55.05"
            ],
            [
              1779055200,
              "54.97"
            ],
            [
              1779055500,
              "54.93"
            ],
            [
              1779055800,
              "54.86"
            ],
            [
              1779056100,
              "54.87"
            ],
            [
              1779056400,
              "54.99"
            ],
            [
              1779056700,
              "54.96"
            ],
            [
              1779057000,
              "54.87"
            ],
            [
              1779057300,
              "54.78"
            ],
            [
              1779057600,
              "54.74"
            ],
            [
              1779057900,
              "54.69"
            ],
            [
              1779058200,
              "54.54"
            ],
            [
              1779058500,
              "54.38"
            ],
            [
              1779058800,
              "54.26"
            ]
          ]
        }
      ]
    }
  }
}